pubtools/_pyxis/__init__.py
pubtools/_pyxis/constants.py
pubtools/_pyxis/pyxis_authentication.py
pubtools/_pyxis/pyxis_client.py
pubtools/_pyxis/pyxis_ops.py
pubtools/_pyxis/pyxis_session.py
pubtools/_pyxis/utils.py
pubtools_pyxis-1.3.7.dist-info/licenses/LICENSE
pubtools_pyxis-1.3.7.dist-info/METADATA
pubtools_pyxis-1.3.7.dist-info/WHEEL
pubtools_pyxis-1.3.7.dist-info/entry_points.txt
pubtools_pyxis-1.3.7.dist-info/top_level.txt
pubtools_pyxis-1.3.7.dist-info/RECORD
