Metadata-Version: 2.4
Name: pubtools-pyxis
Version: 1.3.7
Summary: Pubtools-pyxis
Home-page: https://github.com/release-engineering/pubtools-pyxis
Author: Lubomir Gallovic
Author-email: lgallovi@redhat.com
Classifier: Development Status :: 3 - Alpha
Classifier: Intended Audience :: Developers
Classifier: License :: OSI Approved :: GNU Lesser General Public License v3 (LGPLv3)
Classifier: Programming Language :: Python
Classifier: Programming Language :: Python :: 3
Classifier: Programming Language :: Python :: 3.7
Classifier: Programming Language :: Python :: Implementation :: CPython
Classifier: Programming Language :: Python :: Implementation :: PyPy
Requires-Python: >=3.6
License-File: LICENSE
Requires-Dist: setuptools
Requires-Dist: more-executors>=2.3.0
Requires-Dist: requests
Requires-Dist: requests-kerberos
Requires-Dist: urllib3<2
Provides-Extra: rest
Requires-Dist: Sphinx; extra == "rest"
Dynamic: author
Dynamic: author-email
Dynamic: classifier
Dynamic: description
Dynamic: description-content-type
Dynamic: home-page
Dynamic: license-file
Dynamic: provides-extra
Dynamic: requires-dist
Dynamic: requires-python
Dynamic: summary
